rspy_chess-0.1.0.dist-info/METADATA
rspy_chess-0.1.0.dist-info/WHEEL
rspy_chess-0.1.0.dist-info/licenses/LICENSE
rspy_chess/__init__.py
rspy_chess/rspy_chess.cpython-310-powerpc64le-linux-gnu.so
rspy_chess-0.1.0.dist-info/RECORD
